LICENSE
README.md
__init__.py
client.py
env.yaml.template
requirements.txt
setup.py
digital_ocean_spaces.egg-info/PKG-INFO
digital_ocean_spaces.egg-info/SOURCES.txt
digital_ocean_spaces.egg-info/dependency_links.txt
digital_ocean_spaces.egg-info/requires.txt
digital_ocean_spaces.egg-info/top_level.txt
utils/__init__.py
utils/shell.py