Metadata-Version: 2.1
Name: digital-ocean-spaces
Version: 0.1.5
Summary: An MIT licensed python client for Digital Ocean Spaces with a built in shell.
Home-page: https://github.com/ChariotDev/digital-ocean-spaces
Author: Jody Doolittle <https://chariot-dev.com>
License: MIT
Platform: UNKNOWN
License-File: LICENSE
